{
  "meta": {
    "version": "1.0",
    "description": "马斯洛需求层次 → 行业 → 职业 训练课程",
    "levels": [
      "Level 1: 五大需求 → 核心行业",
      "Level 2: 行业细分 → 具体职业",
      "Level 3: 职业间工序关系（跨行业）"
    ]
  },

  "memories": [
    {"text": "人类最基础的需求是生理需求：食物、水、睡眠、呼吸、体温调节。"},
    {"text": "农业是满足人类食物需求的第一产业，包括种植业、畜牧业、渔业。",
     "link_from_idx": 0, "edge_type": "需求供给"},
    {"text": "食品加工业将农产品转化为可食用商品，是从农田到餐桌的关键环节。",
     "link_from_idx": 1, "edge_type": "产业链"},
    {"text": "水利工程和自来水行业保障饮用水供应，净水技术是核心。",
     "link_from_idx": 0, "edge_type": "需求供给"},
    {"text": "纺织服装业满足人类保暖和体温调节需求，从棉花种植到成衣制造。",
     "link_from_idx": 0, "edge_type": "需求供给"},

    {"text": "安全需求是第二层：人身安全、健康、财产安全、工作稳定。"},
    {"text": "医疗卫生行业直接满足健康需求：医院、药企、医疗器械。",
     "link_from_idx": 5, "edge_type": "需求供给"},
    {"text": "建筑业提供住房，是人身安全和遮风挡雨的物理基础。",
     "link_from_idx": 5, "edge_type": "需求供给"},
    {"text": "保险和金融业为财产安全提供风险对冲机制。",
     "link_from_idx": 5, "edge_type": "需求供给"},
    {"text": "公安司法系统维护社会治安，保障人身安全。",
     "link_from_idx": 5, "edge_type": "需求供给"},

    {"text": "社交需求是第三层：友情、爱情、归属感、社群认同。"},
    {"text": "通信和互联网行业是现代社交的基础设施，连接人与人。",
     "link_from_idx": 10, "edge_type": "需求供给"},
    {"text": "餐饮和娱乐行业为社交活动提供场景和载体。",
     "link_from_idx": 10, "edge_type": "需求供给"},
    {"text": "教育行业既满足知识需求，也是重要的社交场所和价值观塑造场。",
     "link_from_idx": 10, "edge_type": "需求供给"},

    {"text": "尊重需求是第四层：成就感、被认可、自信、他人尊重。"},
    {"text": "职业培训和人力资源行业帮助人们获得专业技能和职业晋升。",
     "link_from_idx": 14, "edge_type": "需求供给"},
    {"text": "媒体和出版行业为思想表达和社会认可提供平台。",
     "link_from_idx": 14, "edge_type": "需求供给"},
    {"text": "设计和艺术行业让人通过创造性工作获得自我认同和他人尊重。",
     "link_from_idx": 14, "edge_type": "需求供给"},

    {"text": "自我实现是最高层需求：发挥潜能、追求理想、创造价值。"},
    {"text": "科研和技术创新行业是人类探索未知、推动文明进步的核心。",
     "link_from_idx": 18, "edge_type": "需求供给"},
    {"text": "创业和风险投资生态让人有机会将想法变为现实。",
     "link_from_idx": 18, "edge_type": "需求供给"},
    {"text": "哲学、心理学和宗教帮助人探索生命意义和精神超越。",
     "link_from_idx": 18, "edge_type": "需求供给"},

    {"text": "农民是种植业的核心劳动者，负责播种、施肥、灌溉、收割。",
     "link_from_idx": 1, "edge_type": "行业职业"},
    {"text": "兽医保障畜牧业动物健康，是肉蛋奶供应链的关键支撑。",
     "link_from_idx": 1, "edge_type": "行业职业"},
    {"text": "食品工程师设计加工工艺，确保食品安全和营养保留。",
     "link_from_idx": 2, "edge_type": "行业职业"},
    {"text": "水处理工程师设计净水和污水处理系统，保障饮用水安全。",
     "link_from_idx": 3, "edge_type": "行业职业"},
    {"text": "服装设计师将面料转化为成衣，兼顾功能性和审美。",
     "link_from_idx": 4, "edge_type": "行业职业"},
    {"text": "医生通过诊断和治疗直接解决人的健康问题。",
     "link_from_idx": 6, "edge_type": "行业职业"},
    {"text": "药剂师研发和配制药物，是医疗体系的药品保障。",
     "link_from_idx": 6, "edge_type": "行业职业"},
    {"text": "建筑师设计房屋和公共建筑，平衡安全性、功能和美学。",
     "link_from_idx": 7, "edge_type": "行业职业"},
    {"text": "施工工人将建筑设计变为现实，是建筑业的执行层。",
     "link_from_idx": 7, "edge_type": "行业职业"},
    {"text": "精算师用数学模型为保险产品定价，管理风险。",
     "link_from_idx": 8, "edge_type": "行业职业"},
    {"text": "警察维护治安、侦办案件，是公共安全的一线守护者。",
     "link_from_idx": 9, "edge_type": "行业职业"},
    {"text": "软件工程师构建互联网和通信系统的技术基础。",
     "link_from_idx": 11, "edge_type": "行业职业"},
    {"text": "厨师将食材转化为菜品，同时创造社交聚餐的体验核心。",
     "link_from_idx": 12, "edge_type": "行业职业"},
    {"text": "教师传授知识和价值观，塑造下一代的认知能力。",
     "link_from_idx": 13, "edge_type": "行业职业"},
    {"text": "记者和编辑通过媒体报道让公众了解真相，塑造社会认知。",
     "link_from_idx": 16, "edge_type": "行业职业"},
    {"text": "科学家通过实验和理论研究推动人类对自然的理解。",
     "link_from_idx": 19, "edge_type": "行业职业"},
    {"text": "创业者将创新想法商业化，创造新的就业机会和社会价值。",
     "link_from_idx": 20, "edge_type": "行业职业"},

    {"text": "农民种出粮食 → 食品工程师加工 → 物流配送 → 厨师烹饪 → 消费者享用。这是从农田到餐桌的完整供应链。",
     "link_from_idx": 22, "edge_type": "工序链"},
    {"text": "建筑师设计 → 施工工人建造 → 水电工安装 → 物业管理维护。这是房屋从图纸到入住的完整流程。",
     "link_from_idx": 30, "edge_type": "工序链"},
    {"text": "科学家发现原理 → 工程师开发技术 → 创业者商业化 → 市场营销推广。这是从基础研究到产品的价值转化链。",
     "link_from_idx": 38, "edge_type": "工序链"}
  ],

  "dialogues": [
    ["人类最基本的需求是什么？", "生理需求是最基础的：食物、水、睡眠、呼吸。没有这些，人无法生存。"],
    ["哪些行业在满足人的基本生存需求？", "农业提供食物，水利工程保障饮水，纺织业提供保暖衣物，建筑业提供遮风挡雨的住所。"],
    ["为什么安全需求排在第二位？", "只有吃饱穿暖后，人才会关注健康、财产和人身安全。医疗、保险、公安系统都在满足这层需求。"],
    ["社交需求具体指什么？", "友情、爱情、归属感。通信行业连接人际关系，餐饮娱乐提供社交场景，教育提供价值认同。"],
    ["怎么理解尊重需求？", "人需要被认可和尊重。职业培训帮助获得专业能力，媒体提供表达平台，创造性工作给人成就感。"],
    ["自我实现是什么意思？", "发挥最大潜能，做自己真正热爱的事。科研探索未知，创业实现想法，艺术表达灵魂。"],

    ["食物是怎么从农田到达我们餐桌的？", "农民种植→食品工程师加工→物流运输→厨师烹饪→消费者享用。每个环节都有专业的人在工作。"],
    ["一栋房子是怎么从无到有的？", "建筑师设计图纸→施工工人浇筑建造→水电工安装管线→装修工程→物业管理维护。"],
    ["一个科学发现怎么变成产品？", "科学家发现原理→工程师开发技术→创业者商业化→市场营销推广→消费者使用。这是完整的价值转化链。"],
    ["医生和药剂师是什么关系？", "医生负责诊断病因和制定治疗方案，药剂师负责研发和配制对症的药物。两者协作才能完成治疗。"],
    ["软件工程师为什么重要？", "现代社交、商业、教育都依赖互联网。软件工程师构建这些数字基础设施，连接了所有人。"],
    ["为什么需要保险？", "人生充满不确定性。精算师用数学模型为风险定价，保险将个体风险分散到群体，提供财务安全网。"],

    ["教师和科学家有什么联系？", "教师培养下一代的认知能力和好奇心，科学家将这种好奇心转化为对自然的系统研究。教育是科研的上游。"],
    ["创业者需要哪些支持？", "需要科学家的技术突破、工程师的产品开发、设计师的用户体验、市场营销的推广、投资人的资金支持。"],
    ["警察和法官是什么关系？", "警察负责维护治安和侦办案件，法官负责依法审判。两者共同构成社会公正体系的执行和裁决环节。"],
    ["农业和医疗有关系吗？", "有。营养学连接了两者——合理的膳食是预防疾病的第一道防线。食品安全问题也需要医疗系统应对。"]
  ],

  "test_queries": [
    "人类有哪些基本需求？",
    "食物是怎么到达我们手上的？",
    "建一栋房子需要哪些人协作？",
    "医疗行业有哪些核心职业？",
    "为什么教育很重要？",
    "科学发现怎么变成商品？"
  ]
}
